dronnai/__init__.py
dronnai/augmentation.py
dronnai/bucketiterator.py
dronnai/early_stopping.py
dronnai/error_analysis.py
dronnai/exp_recorder.py
dronnai/gradients_clipping.py
dronnai/gym.py
dronnai/lr_search.py
dronnai/lr_update.py
dronnai/metric.py
dronnai/split.py
dronnai-0.2.3.dist-info/METADATA
dronnai-0.2.3.dist-info/WHEEL
dronnai-0.2.3.dist-info/top_level.txt
dronnai-0.2.3.dist-info/RECORD
