Metadata-Version: 2.1
Name: dronnai
Version: 0.2.3
Summary: Neural Networks Training Center by Dronn.com
Home-page: https://bitbucket.org/inboxliberatorteam/gym/src/master/
Author: Dronn AI Team
Author-email: info@dronn.com
License: UNKNOWN
Platform: UNKNOWN
Requires-Dist: numpy
Requires-Dist: pandas
Requires-Dist: torch
Requires-Dist: torchtext
Requires-Dist: spacy
Requires-Dist: scikit-learn
Requires-Dist: tqdm
Requires-Dist: flatten-dict
Requires-Dist: sacred
Requires-Dist: tensorboardX
